gsextract/__init__.py
gsextract/gse_parser.py
gsextract/gsextract.py
gsextract/pcaplib.py
gsextract/parsers/__init__.py
gsextract/parsers/icmp_packet.py
gsextract/parsers/ipv4_packet.py
gsextract/parsers/ipv6_packet.py
gsextract/parsers/pure_bb.py
gsextract/parsers/pure_gse.py
gsextract/parsers/tcp_segment.py
gsextract/parsers/udp_datagram.py
gsextract-1.0.dist-info/METADATA
gsextract-1.0.dist-info/WHEEL
gsextract-1.0.dist-info/entry_points.txt
gsextract-1.0.dist-info/top_level.txt
gsextract-1.0.dist-info/RECORD
