Metadata-Version: 2.1
Name: gsextract
Version: 1.0
Summary: A tool to parse corrupted recordings of satellite internet traffic in the GSE over DVB-S format into .pcaps
Home-page: https://github.com/ssloxford/gsextract
Author: James Pavur
Author-email: james.pavur@cs.ox.ac.uk
License: UNKNOWN
Platform: UNKNOWN
Classifier: Programming Language :: Python :: 3
Classifier: License :: OSI Approved :: MIT License
Classifier: Operating System :: OS Independent
Classifier: Intended Audience :: Science/Research
Classifier: Topic :: Security
Requires-Dist: kaitaistruct
Requires-Dist: click
Requires-Dist: scapy
